LICENSE
README.md
setup.py
planet_basemap/__init__.py
planet_basemap/planet_basemap.py
planet_basemap.egg-info/PKG-INFO
planet_basemap.egg-info/SOURCES.txt
planet_basemap.egg-info/dependency_links.txt
planet_basemap.egg-info/entry_points.txt
planet_basemap.egg-info/requires.txt
planet_basemap.egg-info/top_level.txt
planet_basemap/mosaic/__init__.py
planet_basemap/mosaic/download.py
planet_basemap/mosaic/geom_rbox.py
planet_basemap/mosaic/metadata.py
test/__init__.py
test/tests.py