Metadata-Version: 2.1
Name: planet-basemap
Version: 1.0.1
Summary: Tool to download Planet Monthly Mosaic Quads
Home-page: https://github.com/SatAgro/planet-basemap
Author: Krzysztof Stopa
Author-email: krzysztof.stopa@satagro.pl
License: Apache 2.0
Classifier: Development Status :: 4 - Beta
Classifier: Intended Audience :: Developers
Classifier: Intended Audience :: Science/Research
Classifier: Natural Language :: English
Classifier: License :: OSI Approved :: Apache Software License
Classifier: Programming Language :: Python
Classifier: Programming Language :: Python :: 3.8
Classifier: Operating System :: OS Independent
Classifier: Topic :: Scientific/Engineering :: GIS
License-File: LICENSE
